llmonkey/__init__.py
llmonkey/llmonkey.py
llmonkey/models.py
llmonkey/llms/__init__.py
llmonkey/llms/azure.py
llmonkey/llms/base_llm.py
llmonkey/llms/deepinfra.py
llmonkey/llms/google.py
llmonkey/llms/groq.py
llmonkey/llms/ionos.py
llmonkey/llms/mistral.py
llmonkey/llms/nebius.py
llmonkey/llms/openai.py
llmonkey/providers/__init__.py
llmonkey/providers/azure.py
llmonkey/providers/base.py
llmonkey/providers/cohere.py
llmonkey/providers/google.py
llmonkey/providers/groq.py
llmonkey/providers/openai_like.py
llmonkey/recipes/llm_mixins.py
llmonkey/tests/__init__.py
llmonkey/tests/test_main_interface.py
llmonkey/utils/__init__.py
llmonkey/utils/decorators.py
llmonkey-1.0.2.dist-info/licenses/LICENSE.md
llmonkey-1.0.2.dist-info/METADATA
llmonkey-1.0.2.dist-info/WHEEL
llmonkey-1.0.2.dist-info/top_level.txt
llmonkey-1.0.2.dist-info/RECORD
