Metadata-Version: 2.4
Name: llmonkey
Version: 1.0.2
Summary: A library to talk to different language models
Author-email: Andrii Trelin <andrii@absclust.com>
Classifier: Programming Language :: Python :: 3
Classifier: License :: OSI Approved :: MIT License
Classifier: Operating System :: OS Independent
Requires-Python: >=3.10
License-File: LICENSE.md
Requires-Dist: pydantic>=2.8.0
Requires-Dist: python_dotenv>=1.0.0
Requires-Dist: pyyaml>=6.0.2
Requires-Dist: ratelimit>=2.2.0
Requires-Dist: requests>=2.32.0
Requires-Dist: google-cloud-aiplatform>=1.64
Requires-Dist: openai>=1.58.1
Requires-Dist: json-repair
Dynamic: license-file
